python_servo_gpiod/__init__.py
python_servo_gpiod/servo.py
python_servo_gpiod/test_servo.py
python_servo_gpiod-1.1.1.dist-info/licenses/LICENSE.md
python_servo_gpiod-1.1.1.dist-info/METADATA
python_servo_gpiod-1.1.1.dist-info/WHEEL
python_servo_gpiod-1.1.1.dist-info/entry_points.txt
python_servo_gpiod-1.1.1.dist-info/top_level.txt
python_servo_gpiod-1.1.1.dist-info/RECORD
