Metadata-Version: 2.4
Name: python-servo-gpiod
Version: 1.1.1
Summary: A comprehensive Python library for controlling servo motors using gpiod on Linux systems
Author-email: Svndsn <simon.egeris.svendsen@gmail.com>
License: MIT
Project-URL: Homepage, https://github.com/Svndsn/python-servo
Project-URL: Repository, https://github.com/Svndsn/python-servo
Project-URL: Documentation, https://github.com/Svndsn/python-servo#readme
Project-URL: Bug Tracker, https://github.com/Svndsn/python-servo/issues
Keywords: servo,motor,control,gpio,gpiod,raspberry-pi,pwm,hardware
Classifier: Development Status :: 5 - Production/Stable
Classifier: Intended Audience :: Developers
Classifier: Intended Audience :: Education
Classifier: Operating System :: POSIX :: Linux
Classifier: Programming Language :: Python :: 3
Classifier: Programming Language :: Python :: 3.9
Classifier: Programming Language :: Python :: 3.10
Classifier: Programming Language :: Python :: 3.11
Classifier: Programming Language :: Python :: 3.12
Classifier: Topic :: Scientific/Engineering
Classifier: Topic :: Software Development :: Libraries :: Python Modules
Classifier: Topic :: System :: Hardware
Classifier: Topic :: System :: Hardware :: Hardware Drivers
Requires-Python: >=3.9
License-File: LICENSE.md
Requires-Dist: gpiod>=2.0
Provides-Extra: test
Requires-Dist: pytest>=6.0; extra == "test"
Requires-Dist: pytest-cov; extra == "test"
Provides-Extra: dev
Requires-Dist: black; extra == "dev"
Requires-Dist: flake8; extra == "dev"
Requires-Dist: mypy; extra == "dev"
Requires-Dist: pytest>=6.0; extra == "dev"
Requires-Dist: pytest-cov; extra == "dev"
Dynamic: license-file
